{
    "type" : "minecraft:crafting_shaped",
    "conditions": [
        {
            "type" : "minecraft:item_exists",
            "item" : "autoverse:buffer"
        }
    ],
    "group" : "autoverse:buffer",
    "result" :
    {
        "item" : "autoverse:buffer",
        "data" : 0,
        "count" : 4
    },
    "pattern":
    [
        "CCC",
        "HEH",
        "CCC"
    ],
    "key":
    {
        "C" : { "item" : "#COBBLESTONE" },
        "E" : { "item" : "#ORE_CHEST_WOOD" },
        "H" : { "item" : "#HOPPER" }
    }
}